simple_graph_sqlite/__init__.py
simple_graph_sqlite/database.py
simple_graph_sqlite/visualizers.py
simple_graph_sqlite/sql/delete-edge.sql
simple_graph_sqlite/sql/delete-node.sql
simple_graph_sqlite/sql/insert-edge.sql
simple_graph_sqlite/sql/insert-node.sql
simple_graph_sqlite/sql/schema.sql
simple_graph_sqlite/sql/search-edges-inbound.sql
simple_graph_sqlite/sql/search-edges-outbound.sql
simple_graph_sqlite/sql/search-edges.sql
simple_graph_sqlite/sql/search-node.template
simple_graph_sqlite/sql/search-where.template
simple_graph_sqlite/sql/traverse.template
simple_graph_sqlite/sql/update-node.sql
simple_graph_sqlite-2.1.0.dist-info/LICENSE
simple_graph_sqlite-2.1.0.dist-info/METADATA
simple_graph_sqlite-2.1.0.dist-info/WHEEL
simple_graph_sqlite-2.1.0.dist-info/top_level.txt
simple_graph_sqlite-2.1.0.dist-info/RECORD
