Metadata-Version: 2.1
Name: simple-graph-sqlite
Version: 2.1.0
Summary: A simple graph database in SQLite
Home-page: https://github.com/dpapathanasiou/simple-graph-pypi
Author: Denis Papathanasiou
Project-URL: Bug Reports, https://github.com/dpapathanasiou/simple-graph-pypi/issues
Project-URL: Source, https://github.com/dpapathanasiou/simple-graph-pypi/tree/main/src/simple_graph_sqlite
Requires-Python: >=3.6, <4
License-File: LICENSE
Requires-Dist: graphviz
Requires-Dist: Jinja2
Provides-Extra: test
Requires-Dist: pytest ; extra == 'test'
